lightweightpush/__init__.py
lightweightpush/lightweightpush.py
lightweightpush-0.1.0.dist-info/LICENSE
lightweightpush-0.1.0.dist-info/METADATA
lightweightpush-0.1.0.dist-info/WHEEL
lightweightpush-0.1.0.dist-info/top_level.txt
lightweightpush-0.1.0.dist-info/RECORD
