Metadata-Version: 2.1
Name: lightweightpush
Version: 0.1.0
Summary: A simple, end-to-end encrypted and easy to use push service for messages.
Home-page: https://github.com/sqall01/lightweight-push-pip
Author: Andre Pawlowski (sqall)
Author-email: pypi-sqall@h4des.org
Classifier: Programming Language :: Python :: 3
Classifier: License :: OSI Approved :: MIT License
Classifier: Operating System :: OS Independent
License-File: LICENSE
Requires-Dist: pycryptodome (>=3.16.0)
Requires-Dist: requests (>=2.28.1)
